better_jupyter_mcp_server/__env__.py
better_jupyter_mcp_server/__init__.py
better_jupyter_mcp_server/config.toml
better_jupyter_mcp_server/server.py
better_jupyter_mcp_server/utils/__init__.py
better_jupyter_mcp_server/utils/cell.py
better_jupyter_mcp_server/utils/formatter.py
better_jupyter_mcp_server/utils/notebook.py
iflow_mcp_jupyter_server-1.4.12.dist-info/METADATA
iflow_mcp_jupyter_server-1.4.12.dist-info/WHEEL
iflow_mcp_jupyter_server-1.4.12.dist-info/entry_points.txt
iflow_mcp_jupyter_server-1.4.12.dist-info/licenses/LICENSE
iflow_mcp_jupyter_server-1.4.12.dist-info/RECORD
