Metadata-Version: 2.4
Name: iflow-mcp-jupyter-server
Version: 1.4.12
Summary: A powerful MCP server for AI-driven Jupyter Notebook management and execution
Project-URL: Homepage, https://github.com/ChengJiale150/jupyter-mcp-server
Project-URL: Repository, https://github.com/ChengJiale150/jupyter-mcp-server
Project-URL: Documentation, https://github.com/ChengJiale150/jupyter-mcp-server/blob/main/README.md
Project-URL: Issues, https://github.com/ChengJiale150/jupyter-mcp-server/issues
License: MIT
License-File: LICENSE
Keywords: ai,data-science,jupyter,machine-learning,mcp,model-context-protocol,notebook
Classifier: Development Status :: 4 - Beta
Classifier: Framework :: Jupyter
Classifier: Intended Audience :: Developers
Classifier: Intended Audience :: Science/Research
Classifier: License :: OSI Approved :: MIT License
Classifier: Operating System :: OS Independent
Classifier: Programming Language :: Python :: 3
Classifier: Programming Language :: Python :: 3.12
Classifier: Programming Language :: Python :: 3.13
Classifier: Topic :: Scientific/Engineering
Classifier: Topic :: Software Development :: Libraries :: Python Modules
Classifier: Topic :: System :: Shells
Requires-Python: >=3.12
Requires-Dist: datalayer-pycrdt>=0.12.17
Requires-Dist: fastmcp>=2.12.2
Requires-Dist: jupyter-collaboration>=4.1.1
Requires-Dist: jupyter-kernel-client>=0.8.0
Requires-Dist: jupyter-nbmodel-client>=0.14.2
Requires-Dist: jupyter-server-api>=0.1.0
Requires-Dist: nbformat>=5.10.4
Requires-Dist: pillow>=10.0.0
